{
  "width": 12,
  "height": 12,
  "spaces": [

    {
      "actions": [
        {
          "CLASSNAME": "dk.dtu.compute.se.pisd.roborally.model.ConveyorBelt",
          "INSTANCE": {
            "heading": "SOUTH"
          }
        }
      ],
      "x": 8,
      "y": 3
    },
    {
      "actions": [
        {
          "CLASSNAME": "dk.dtu.compute.se.pisd.roborally.model.ConveyorBelt",
          "INSTANCE": {
            "heading": "SOUTH"
          }
        }
      ],
      "x": 8,
      "y": 4
    },
    {
      "actions": [
        {
          "CLASSNAME": "dk.dtu.compute.se.pisd.roborally.model.ConveyorBelt",
          "INSTANCE": {
            "heading": "SOUTH"
          }
        }
      ],
      "x": 8,
      "y": 5,
    },
    {
      "actions": [
        {
          "CLASSNAME": "dk.dtu.compute.se.pisd.roborally.model.ConveyorBelt",
          "INSTANCE": {
            "heading": "SOUTH"
          }
        }
      ],
      "x": 8,
      "y": 6
    },
    {
      "actions": [
        {
          "CLASSNAME": "dk.dtu.compute.se.pisd.roborally.model.ConveyorBelt",
          "INSTANCE": {
            "heading": "NORTH"
          }
        }
      ],
      "x": 4,
      "y": 7
    },
    {
      "actions": [
        {
          "CLASSNAME": "dk.dtu.compute.se.pisd.roborally.model.ConveyorBelt",
          "INSTANCE": {
            "heading": "NORTH"
          }
        }
      ],
      "x": 4,
      "y": 6
    },
    {
      "actions": [
        {
          "CLASSNAME": "dk.dtu.compute.se.pisd.roborally.model.ConveyorBelt",
          "INSTANCE": {
            "heading": "NORTH"
          }
        }
      ],
      "x": 4,
      "y": 5
    },
    {
      "actions": [
        {
          "CLASSNAME": "dk.dtu.compute.se.pisd.roborally.model.ConveyorBelt",
          "INSTANCE": {
            "heading": "NORTH"
          }
        }
      ],
      "x": 4,
      "y": 4
    },
    {
      "actions": [
        {
          "CLASSNAME": "dk.dtu.compute.se.pisd.roborally.model.ConveyorBelt",
          "INSTANCE": {
            "heading": "EAST"
          }
        }
      ],
      "x": 4,
      "y": 3
    },
    {
      "actions": [
        {
          "CLASSNAME": "dk.dtu.compute.se.pisd.roborally.model.ConveyorBelt",
          "INSTANCE": {
            "heading": "EAST"
          }
        }
      ],
      "x": 5,
      "y": 3
    },
    {
      "actions": [
        {
          "CLASSNAME": "dk.dtu.compute.se.pisd.roborally.model.ConveyorBelt",
          "INSTANCE": {
            "heading": "EAST"
          }
        }
      ],
      "x": 6,
      "y": 3
    },
    {
      "actions": [
        {
          "CLASSNAME": "dk.dtu.compute.se.pisd.roborally.model.ConveyorBelt",
          "INSTANCE": {
            "heading": "EAST"
          }
        }
      ],
      "x": 7,
      "y": 3
    },
    {
      "actions": [
        {
          "CLASSNAME": "dk.dtu.compute.se.pisd.roborally.model.ConveyorBelt",
          "INSTANCE": {
            "heading": "WEST"
          }
        }
      ],
      "x": 8,
      "y": 7
    },
    {
      "actions": [
        {
          "CLASSNAME": "dk.dtu.compute.se.pisd.roborally.model.ConveyorBelt",
          "INSTANCE": {
            "heading": "WEST"
          }
        }
      ],
      "x": 7,
      "y": 7
    },
    {
      "actions": [
        {
          "CLASSNAME": "dk.dtu.compute.se.pisd.roborally.model.ConveyorBelt",
          "INSTANCE": {
            "heading": "WEST"
          }
        }
      ],
      "x": 5,
      "y": 7
    }
  ]
}